titiler/extensions/__init__.py
titiler/extensions/cogeo.py
titiler/extensions/py.typed
titiler/extensions/render.py
titiler/extensions/stac.py
titiler/extensions/viewer.py
titiler/extensions/wms.py
titiler/extensions/wmts.py
titiler/extensions/templates/cog_viewer.html
titiler/extensions/templates/stac_viewer.html
titiler/extensions/templates/wms_1.0.0.xml
titiler/extensions/templates/wms_1.1.1.xml
titiler/extensions/templates/wms_1.3.0.xml
titiler/extensions/templates/wmts.xml
titiler_extensions-1.0.2.dist-info/METADATA
titiler_extensions-1.0.2.dist-info/WHEEL
titiler_extensions-1.0.2.dist-info/licenses/LICENSE
titiler_extensions-1.0.2.dist-info/RECORD
