Metadata-Version: 2.4
Name: titiler-extensions
Version: 1.0.2
Summary: Extensions for TiTiler Factories.
Project-URL: Homepage, https://developmentseed.org/titiler/
Project-URL: Documentation, https://developmentseed.org/titiler/
Project-URL: Issues, https://github.com/developmentseed/titiler/issues
Project-URL: Source, https://github.com/developmentseed/titiler
Project-URL: Changelog, https://developmentseed.org/titiler/release-notes/
Author-email: Vincent Sarago <vincent@developmentseed.com>
License: MIT
License-File: LICENSE
Keywords: COG,Dynamic tile server,Fastapi,GDAL,MosaicJSON,OGC,Rasterio,STAC
Classifier: Intended Audience :: Information Technology
Classifier: Intended Audience :: Science/Research
Classifier: License :: OSI Approved :: MIT License
Classifier: Programming Language :: Python :: 3
Classifier: Programming Language :: Python :: 3.11
Classifier: Programming Language :: Python :: 3.12
Classifier: Programming Language :: Python :: 3.13
Classifier: Programming Language :: Python :: 3.14
Classifier: Topic :: Scientific/Engineering :: GIS
Requires-Python: >=3.11
Requires-Dist: titiler-core==1.0.2
Provides-Extra: cogeo
Requires-Dist: rio-cogeo<8.0,>=7.0; extra == 'cogeo'
Provides-Extra: stac
Requires-Dist: rio-stac<0.13,>=0.12; extra == 'stac'
